AUTHORS
CHANGES
LICENSE
MANIFEST.in
README.rst
setup.py
PyDrive3.egg-info/PKG-INFO
PyDrive3.egg-info/SOURCES.txt
PyDrive3.egg-info/dependency_links.txt
PyDrive3.egg-info/requires.txt
PyDrive3.egg-info/top_level.txt
docs/filelist.html
docs/filemanagement.html
docs/genindex.html
docs/index.html
docs/oauth.html
docs/objects.inv
docs/pydrive.html
docs/quickstart.html
docs/search.html
docs/searchindex.js
docs/_sources/filelist.txt
docs/_sources/filemanagement.txt
docs/_sources/index.txt
docs/_sources/oauth.txt
docs/_sources/pydrive.txt
docs/_sources/quickstart.txt
docs/_static/ajax-loader.gif
docs/_static/basic.css
docs/_static/comment-bright.png
docs/_static/comment-close.png
docs/_static/comment.png
docs/_static/default.css
docs/_static/doctools.js
docs/_static/down-pressed.png
docs/_static/down.png
docs/_static/file.png
docs/_static/jquery.js
docs/_static/minus.png
docs/_static/plus.png
docs/_static/pygments.css
docs/_static/searchtools.js
docs/_static/sidebar.js
docs/_static/underscore.js
docs/_static/up-pressed.png
docs/_static/up.png
docs/_static/websupport.js
pydrive/__init__.py
pydrive/apiattr.py
pydrive/auth.py
pydrive/drive.py
pydrive/files.py
pydrive/settings.py
pydrive/test/README.rst
pydrive/test/__init__.py
pydrive/test/test_file.py
pydrive/test/test_filelist.py
pydrive/test/test_oauth.py
pydrive/test/settings/default.yaml
pydrive/test/settings/test1.yaml
pydrive/test/settings/test2.yaml
pydrive/test/settings/test3.yaml
pydrive/test/settings/test4.yaml
pydrive/test/settings/test5.yaml