Metadata-Version: 1.0
Name: PyDrive3
Version: 1.0.0
Summary: Google Drive API made easy.
Home-page: http://pypi.python.org/pypi/PyDrive/
Author: JunYoung Gwak
Author-email: jgwak@dreamylab.com
License: LICENSE
Platform: UNKNOWN
